stratcp/__init__.py
stratcp/eval_utils.py
stratcp/metrics.py
stratcp/stratified.py
stratcp/utils.py
stratcp/conformal/__init__.py
stratcp/conformal/core.py
stratcp/conformal/scores.py
stratcp/conformal/utility.py
stratcp/selection/__init__.py
stratcp/selection/multiple.py
stratcp/selection/single.py
stratcp/selection/survival.py
stratcp-0.1.0.dist-info/METADATA
stratcp-0.1.0.dist-info/WHEEL
stratcp-0.1.0.dist-info/licenses/LICENSE
stratcp-0.1.0.dist-info/RECORD
