Metadata-Version: 2.4
Name: stratcp
Version: 0.1.0
Summary: Stratified Conformal Prediction: A Python package for safe decisions with FDR-control in the action arm and coverage in the deferral arm
Project-URL: Repository, https://github.com/mims-harvard/stratcp
Project-URL: Documentation, https://zitniklab.hms.harvard.edu/stratcp/
Author-email: Ying Jin <yjinstat@wharton.upenn.edu>, Intae Moon <intae_moon@hms.harvard.edu>
License: MIT License
License-File: LICENSE
Keywords: conformal-prediction,fdr-control,machine-learning,post-selection-inference,selective-prediction,uncertainty-quantification
Classifier: Intended Audience :: Developers
Classifier: Intended Audience :: Science/Research
Classifier: Programming Language :: Python
Classifier: Programming Language :: Python :: 3
Classifier: Programming Language :: Python :: 3.9
Classifier: Programming Language :: Python :: 3.10
Classifier: Programming Language :: Python :: 3.11
Classifier: Programming Language :: Python :: 3.12
Classifier: Programming Language :: Python :: 3.13
Classifier: Topic :: Scientific/Engineering :: Artificial Intelligence
Classifier: Topic :: Software Development :: Libraries :: Python Modules
Requires-Python: <4.0,>=3.9
Requires-Dist: jupyter>=1.1.1
Requires-Dist: matplotlib>=3.7.0
Requires-Dist: numpy>=1.24.0
Requires-Dist: pandas>=2.0.0
Requires-Dist: scikit-learn>=1.3.0
Requires-Dist: scipy>=1.10.0
Requires-Dist: seaborn>=0.12.0
Requires-Dist: tqdm>=4.67.1
